nonebot_plugin_tarot/__init__.py
nonebot_plugin_tarot/config.py
nonebot_plugin_tarot/data_source.py
nonebot_plugin_tarot/tarot.json
nonebot_plugin_tarot-0.4.0.post4.dist-info/LICENSE
nonebot_plugin_tarot-0.4.0.post4.dist-info/METADATA
nonebot_plugin_tarot-0.4.0.post4.dist-info/WHEEL
nonebot_plugin_tarot-0.4.0.post4.dist-info/RECORD
