Metadata-Version: 2.1
Name: nonebot-plugin-tarot
Version: 0.4.0.post4
Summary: Tarot divination!
Home-page: https://github.com/MinatoAquaCrews/nonebot_plugin_tarot
License: MIT
Keywords: nonebot2,nonebot-plugin,Tarot,MinatoAquaCrews
Author: KafCoppelia
Author-email: k740677208@gmail.com
Requires-Python: >=3.8,<4.0
Classifier: License :: OSI Approved :: MIT License
Classifier: Programming Language :: Python :: 3
Classifier: Programming Language :: Python :: 3.8
Classifier: Programming Language :: Python :: 3.9
Classifier: Programming Language :: Python :: 3.10
Classifier: Programming Language :: Python :: 3.11
Requires-Dist: aiocache (>=0.11.1,<0.12.0)
Requires-Dist: httpx (>=0.23.0,<0.24.0)
Requires-Dist: nonebot-adapter-onebot (>=2.1.0,<3.0.0)
Requires-Dist: nonebot2 (>=2.0.0b3,<3.0.0)
Requires-Dist: pillow (>=9.0.0,<10.0.0)
Project-URL: Repository, https://github.com/MinatoAquaCrews/nonebot_plugin_tarot
